{
  "hash": "4754b3570d627f390545eed3229da2a0",
  "result": {
    "engine": "jupyter",
    "markdown": "---\ntitle: \"PyTorch로 직접 만드는 커스텀 손실 함수: 핀볼·Huber·CRPS\"\ndate: \"2026-07-17\"\ncategories:\n  - 데이터과학\n  - 인공지능\n  - PyTorch\n  - 시계열\n  - 확률예측\n  - 분위수 회귀\n  - 확률적 예측\ntags:\n  - 커스텀-손실\n  - 핀볼손실\n  - 분위수회귀\n  - Huber손실\n  - CRPS\n  - 확률예측\n  - PyTorch\n  - 강건회귀\n  - 시계열\nimage: \"thumbnail.jpg\"\ndescription: |\n  MSE가 기본 손실이 되어 있는 이유는 편리하기 때문이지 옳기 때문이\n  아닙니다. 이 글은 각기 다른 문제에 맞는 세 가지 손실 — 분위수\n  예측용 핀볼(pinball), 이상치가 있는 회귀용 Huber, 확률 예측용\n  CRPS — 를 작은 PyTorch 모듈로 처음부터 구현하고, 그 기울기와 형태를\n  살펴본 뒤, 합성 데이터 위에서 각각이 MSE와 어떻게 다르게 동작하는지\n  보입니다.\nlang: ko\ntoc: true\ntoc-depth: 3\nnumber-sections: false\ncode-fold: false\ncode-tools: false\nexecute:\n  echo: true\n  output: true\n  eval: true\n  warning: false\n  message: false\n  freeze: true\nformat:\n  html:\n    code-copy: true\n    code-overflow: wrap\n---\n\n![[개념 시각화] 본 포스트의 핵심 개념을 요약한 다이어그램입니다.](thumbnail.jpg){fig-align=\"center\" width=\"90%\"}\n\n\n\n## 기본 손실은 중립적 선택이 아닙니다\n\n대부분의 PyTorch 튜토리얼에서 학습 목적 함수는 `nn.MSELoss()`로\n정해져 있습니다. 매끄럽고 볼록하며 어디서든 미분 가능하고, 조건부\n평균을 최소화한다는 점에서 편리하지만, 이 각각의 성질은 동시에\n하나의 가정이기도 합니다. 조건부 평균이 예측의 정답이 되는 것은\n후속 결정이 제곱오차 결정일 때뿐이고, 큰 오차에 민감한 것이 옳은\n행동인 것은 그 큰 오차가 잡음이 아니라 정보일 때뿐이며, 점 예측\n하나가 충분한 것은 예측의 불확실성을 사용자가 필요로 하지 않을\n때뿐입니다.\n\n시계열 예측은 이 세 가정을 한꺼번에 어깁니다. 소매 수요 계획은\n평균이 아니라 90분위수를 봅니다. 재고 부족과 과잉의 비용이 다르기\n때문입니다. 센서 데이터에는 시계 편이나 하드웨어 결함에서 오는\n이상치가 섞이는데, 이는 모델이 학습해야 할 신호가 아닙니다. 그리고\n그 뒤에 붙는 어떤 리스크 계산이든 — 예비 용량, 제어 여유,\n헤지 규모 — 결국 점 추정치가 아니라 예측 분포 전체의 함수입니다.\n\n세 가지 손실이 부족한 부분 대부분을 채워 줍니다. 비대칭 비용의 점\n예측 및 여러 분위수를 통한 분포 전체 모델링에 쓰이는 *핀볼*\n(pinball, 분위수) 손실, 잡음이 두꺼운 꼬리(heavy tail)를 가질 때\n쓰이는 *Huber* 손실, 그리고 확률 예측을 학습·평가하기 위한 *연속형\n순위 확률 점수(continuous ranked probability score, CRPS)*가 그것입\n니다. 구현 자체는 각각 짧지만, 손실과 그 기울기의 *모양*이 모델이\n실제로 무엇을 배우는지를 결정합니다.\n\n## 손실을 값이 아니라 모양과 기울기로 보기\n\n학습 중 손실의 동작을 결정하는 것은 값 자체가 아니라 기울기입니다.\nMSE와 MAE가 실질적으로 크게 다른 것도 이 때문입니다. 두 손실 모두\n목표 분포의 \"가운데\"에서 최소화되지만, 최소화에 도달하는 방식이\n다릅니다. 구현 전에 네 손실을 나란히 정리해 보는 것이 좋습니다.\n\n$e = y - \\hat{y}$을 부호 있는 오차라 하겠습니다.\n\n$$L_{\\text{MSE}}(e) = \\tfrac{1}{2} e^{2}, \\qquad\n\\frac{\\partial L_{\\text{MSE}}}{\\partial \\hat{y}} = -e.$$\n\n$$L_{\\text{MAE}}(e) = |e|, \\qquad\n\\frac{\\partial L_{\\text{MAE}}}{\\partial \\hat{y}} = -\\operatorname{sign}(e).$$\n\n$$L_{\\tau}(e) = \\max(\\tau e,\\; (\\tau - 1) e), \\qquad\n\\frac{\\partial L_{\\tau}}{\\partial \\hat{y}} =\n\\begin{cases}\n-\\tau & e > 0, \\\\\n\\;1 - \\tau & e < 0,\n\\end{cases}\n\\qquad \\tau \\in (0,1).$$\n\n$$L_{\\delta}^{\\text{Huber}}(e) =\n\\begin{cases}\n\\tfrac{1}{2} e^{2} & |e| \\le \\delta,\\\\\n\\delta \\bigl(|e| - \\tfrac{1}{2}\\delta\\bigr) & |e| > \\delta,\n\\end{cases}\n\\qquad\n\\frac{\\partial L_{\\delta}^{\\text{Huber}}}{\\partial \\hat{y}} =\n\\begin{cases}\n-e & |e| \\le \\delta, \\\\\n-\\delta \\operatorname{sign}(e) & |e| > \\delta.\n\\end{cases}$$\n\nMSE에서 중요한 것은 기울기가 $|e|$에 비례해 무한정 커진다는\n점입니다. $|e|=10$인 한 점의 기울기 크기가 $10$이 되어, $|e|=1$인\n열 점의 합과 같아집니다. 이 성질이 MSE를 학습하기 쉽게 만드는\n이유이자 이상치에서 위험하게 만드는 이유입니다.\n\n핀볼의 기울기는 *구간별 상수*입니다. 분위수 수준 $\\tau$가 주어지면\n모든 저평가는 동일하게 $-\\tau$, 모든 고평가는 동일하게 $1-\\tau$를\n기여합니다. $\\tau$를 선택한다는 것은 이 두 상수의 비율을 정하는\n것이고, 이 비율이 곧 적합선 위·아래의 점 비율을 결정합니다.\n최적해에서 양의 잔차 비율이 정확히 $\\tau$가 되는데, 이는 부산물이\n아니라 손실 정의에 이미 새겨져 있는 성질입니다.\n\nHuber의 기울기는 작은 오차에서 $e$, 큰 오차에서 $\\pm \\delta$로\n잘려 있습니다. MSE와 MAE 사이의 자연스러운 보간입니다. 이미 잘\n맞은 영역(0 근처)에서는 MSE의 매끄러움을 유지해 미세 조정에 도움을\n주고, 이상치 영역(0에서 멀리)에서는 MAE처럼 기울기가 유계여서\n튀는 값이 학습을 지배하지 못하게 합니다.\n\n이 모두를 하나의 그림으로 그려 봅니다.\n\n::: {#cell-fig-loss-shapes .cell execution_count=1}\n``` {.python .cell-code}\nimport torch\nimport matplotlib.pyplot as plt\n\ne = torch.linspace(-3, 3, 601)\n\ndef pinball_val(e, tau):\n    return torch.maximum(tau * e, (tau - 1.0) * e)\n\ndef huber_val(e, delta):\n    a = e.abs()\n    return torch.where(a <= delta, 0.5 * e * e, delta * (a - 0.5 * delta))\n\nfig, axes = plt.subplots(2, 3, figsize=(11, 6.4))\n\n# 상단: 손실 값\naxes[0, 0].plot(e, 0.5 * e ** 2, lw=2, label=\"MSE (½e²)\")\naxes[0, 0].plot(e, e.abs(),      lw=2, ls=\"--\", label=\"MAE (|e|)\")\naxes[0, 0].set_title(\"MSE vs MAE\"); axes[0, 0].legend(); axes[0, 0].grid(alpha=0.3)\n\nfor tau in (0.1, 0.5, 0.9):\n    axes[0, 1].plot(e, pinball_val(e, tau), lw=2, label=f\"τ={tau}\")\naxes[0, 1].set_title(\"Pinball loss\"); axes[0, 1].legend(); axes[0, 1].grid(alpha=0.3)\n\nfor d in (0.3, 1.0, 3.0):\n    axes[0, 2].plot(e, huber_val(e, d), lw=2, label=f\"δ={d}\")\naxes[0, 2].plot(e, 0.5 * e ** 2, lw=1, ls=\":\", color=\"grey\", label=\"MSE ref\")\naxes[0, 2].set_title(\"Huber loss\"); axes[0, 2].legend(); axes[0, 2].grid(alpha=0.3)\n\n# 하단: 예측에 대한 기울기 (= -dL/de)\naxes[1, 0].plot(e, -e,             lw=2, label=\"dMSE/dŷ = -e\")\naxes[1, 0].plot(e, -torch.sign(e), lw=2, ls=\"--\", label=\"dMAE/dŷ = -sign(e)\")\naxes[1, 0].axhline(0, color=\"k\", lw=0.5); axes[1, 0].legend(); axes[1, 0].grid(alpha=0.3)\naxes[1, 0].set_title(\"MSE vs MAE gradient\")\n\nfor tau in (0.1, 0.5, 0.9):\n    g = torch.where(e >= 0, torch.tensor(-tau), torch.tensor(1.0 - tau))\n    axes[1, 1].plot(e, g, lw=2, drawstyle=\"steps-mid\", label=f\"τ={tau}\")\naxes[1, 1].axhline(0, color=\"k\", lw=0.5); axes[1, 1].legend(); axes[1, 1].grid(alpha=0.3)\naxes[1, 1].set_title(\"Pinball gradient (piecewise constant)\")\n\nfor d in (0.3, 1.0, 3.0):\n    g = torch.where(e.abs() <= d, -e, -d * torch.sign(e))\n    axes[1, 2].plot(e, g, lw=2, label=f\"δ={d}\")\naxes[1, 2].axhline(0, color=\"k\", lw=0.5); axes[1, 2].legend(); axes[1, 2].grid(alpha=0.3)\naxes[1, 2].set_title(\"Huber gradient (clipped linear)\")\n\nfor ax in axes[-1]:\n    ax.set_xlabel(\"error e = y - ŷ\")\nfig.tight_layout()\nplt.show()\n```\n\n::: {.cell-output .cell-output-display}\n![MSE·MAE·핀볼(세 분위수)·Huber(세 δ)의 손실 값(상단)과 예측에 대한 기울기(하단).](index_files/figure-html/fig-loss-shapes-output-1.png){#fig-loss-shapes width=1046 height=605}\n:::\n:::\n\n\n그림에서 두 가지를 읽을 수 있습니다. 첫째, 핀볼은 $\\tau=0.5$에서\n$|e|/2$와 같아집니다. 중앙값 회귀가 분위수 회귀의 특수 경우임을\n보여 주며, 핀볼 기울기 세 개는 우측에서 $-\\tau$, 좌측에서 $1-\\tau$의\n수평선인데, 이 상수 비율이 곧 적합 후 양의 잔차 비율을 결정한다는\n사실이 한눈에 들어옵니다. 둘째, Huber의 전이는 $|e|=\\delta$에서\n값은 매끄럽지만 기울기는 꺾여 있습니다. $\\delta$가 작으면 손실이\nMAE에 가까워지고, 아주 크면 MSE로 복원되며, 일반적인 선택은 잡음\n표준편차의 1~2배 정도입니다.\n\n## 핀볼 손실과 분위수 예측\n\n특성 $X$가 주어졌을 때 확률변수 $Y$의 조건부 $\\tau$-분위수\n$\\hat{q}_\\tau(X)$를 예측하려 한다고 합시다. Koenker와 Bassett(1978)\n은 핀볼 위험의 모집단 최소화가 정확히 이 조건부 분위수임을 보였습니다:\n\n$$\\hat{q}_\\tau(x) = \\arg\\min_{f} \\; \\mathbb{E}\\bigl[ L_\\tau(Y - f(X)) \\mid X = x \\bigr].$$\n\n코드로 옮기면 결과는 아주 직접적입니다. MSE를 핀볼($\\tau=0.9$)로\n교체하면, 같은 아키텍처·같은 옵티마이저 위에서 출력값이 곧 90분위수가\n되는 네트워크가 학습됩니다.\n\n::: {#pinball-module .cell execution_count=2}\n``` {.python .cell-code}\nimport torch\nimport torch.nn as nn\n\nclass PinballLoss(nn.Module):\n    \"\"\"\n    Pinball (quantile) loss.\n    - tau가 스칼라이면 단일 분위수 손실, 예측 shape은 (..., ).\n    - tau가 길이 K의 1D 텐서이면 예측의 마지막 차원이 K여야 하고,\n      target은 마지막 차원으로 브로드캐스팅됩니다.\n    \"\"\"\n    def __init__(self, tau, reduction: str = \"mean\"):\n        super().__init__()\n        tau = torch.as_tensor(tau, dtype=torch.float32)\n        self.register_buffer(\"tau\", tau)\n        self.reduction = reduction\n\n    def forward(self, pred: torch.Tensor, target: torch.Tensor) -> torch.Tensor:\n        # multi-quantile head인 경우 target을 마지막 축으로 브로드캐스팅\n        if self.tau.ndim == 1 and pred.shape[-1] == self.tau.numel():\n            target = target.unsqueeze(-1)\n        e = target - pred\n        loss = torch.maximum(self.tau * e, (self.tau - 1.0) * e)\n        if self.reduction == \"mean\":  return loss.mean()\n        if self.reduction == \"sum\":   return loss.sum()\n        return loss\n```\n:::\n\n\n구현에서 짚을 만한 두 가지가 있습니다. 하나는 $e=0$에서 열등미분\n(subgradient)이 유일하지 않다는 점입니다. `torch.maximum`은 두 가지를\n어느 쪽인가로 결정하는데, 핀볼에서는 이 결정이 상관없습니다. 등가\n집합의 측도가 0이기 때문입니다. 또 하나는 `tau`를 학습 파라미터가\n아닌 버퍼로 등록해 두면 `.to(device)` 시 함께 이동한다는 위생상의\n이점입니다.\n\n분위수 성질을 직접 확인하기 위해, 잡음의 분산이 $|x|$에 따라 커지는\n이분산(heteroscedastic) 데이터 위에서 $\\tau \\in \\{0.1, 0.5, 0.9\\}$\n용 세 개의 출력 헤드를 가진 공유 MLP를 학습시킵니다.\n\n::: {#cell-fig-quantile-bands .cell execution_count=3}\n``` {.python .cell-code}\nimport torch\nimport torch.nn as nn\nimport matplotlib.pyplot as plt\n\ntorch.manual_seed(0)\n\n# 데이터: y = 1.5 sin(x) + N(0, sigma(x)^2), sigma(x) = 0.3 + 0.4|x|\nn = 500\nx = torch.linspace(-2, 2, n).unsqueeze(1)\nsigma = 0.3 + 0.4 * x.abs()\ny = 1.5 * torch.sin(x) + sigma * torch.randn_like(x)\ny = y.squeeze(1)\n\ntaus = torch.tensor([0.1, 0.5, 0.9])\nK = taus.numel()\n\nclass QuantileMLP(nn.Module):\n    def __init__(self, K=3, hidden=32):\n        super().__init__()\n        self.trunk = nn.Sequential(\n            nn.Linear(1, hidden), nn.ReLU(),\n            nn.Linear(hidden, hidden), nn.ReLU(),\n        )\n        self.head = nn.Linear(hidden, K)\n\n    def forward(self, x):\n        return self.head(self.trunk(x))\n\nmodel = QuantileMLP(K=K)\nopt = torch.optim.Adam(model.parameters(), lr=0.01)\ncrit = PinballLoss(tau=taus)\n\nfor step in range(3000):\n    opt.zero_grad()\n    pred = model(x)                          # (n, K)\n    loss = crit(pred, y)\n    loss.backward()\n    opt.step()\n\nwith torch.no_grad():\n    pred = model(x).numpy()\n\n# 학습 데이터 위에서 80% 밴드의 실제 커버리지\ncovered = ((y.numpy() >= pred[:, 0]) & (y.numpy() <= pred[:, 2])).mean()\nprint(f\"Final pinball loss: {loss.item():.4f}\")\nprint(f\"Empirical coverage of 80% band on training data: {covered:.3f}\")\n\nxs = x.numpy().ravel()\ntrue_mean = (1.5 * torch.sin(x)).numpy().ravel()\nfig, ax = plt.subplots(figsize=(7, 4.2))\nax.scatter(xs, y.numpy(), s=8, alpha=0.4, label=\"data (heteroscedastic)\")\nax.fill_between(xs, pred[:, 0], pred[:, 2], alpha=0.2, label=\"80% band (τ=0.1–0.9)\")\nax.plot(xs, pred[:, 1], lw=2, label=\"median (τ=0.5)\")\nax.plot(xs, true_mean, \"k--\", lw=1.5, label=\"true mean\")\nax.legend(); ax.grid(alpha=0.3)\nax.set_xlabel(\"x\"); ax.set_ylabel(\"y\")\nax.set_title(\"Quantile bands from a shared MLP trained with pinball loss\")\nplt.show()\n```\n\n::: {.cell-output .cell-output-stdout}\n```\nFinal pinball loss: 0.1725\nEmpirical coverage of 80% band on training data: 0.812\n```\n:::\n\n::: {.cell-output .cell-output-display}\n![핀볼 손실을 결합해 학습한 MLP의 10/50/90 분위수 밴드. 파란 영역은 10-90 구간, 검정 점선은 참 평균.](index_files/figure-html/fig-quantile-bands-output-2.png){#fig-quantile-bands width=587 height=390}\n:::\n:::\n\n\n그림에서 두 가지를 볼 수 있습니다. 잡음이 커지는 구간에서 밴드가\n넓어집니다. 10분위수와 90분위수 헤드가 각자의 조건부 분위수를 쫓기\n때문에, 분산 모델을 따로 명시하지 않아도 손실이 이분산 구조를 자동으로\n포착합니다. 그리고 위에서 출력된 실제 커버리지는 $\\tau_{0.9} -\n\\tau_{0.1} = 0.8$에 가깝게 나옵니다. 손실이 잘 최적화되었다면 학습\n셋 위에서 기대되는 값이며, 여기서 큰 편차가 있다면 두 헤드가 서로\n교차했거나 모델이 목표 분위수까지 유연하게 도달하지 못한 신호로\n보아야 합니다.\n\n헤드 교차(head crossing)는 독립 분위수 적합의 주된 병리입니다. 세\n헤드가 서로 별개로 학습되기 때문에, 학습 목적 함수 안에서\n$\\hat{q}_{0.1} \\le \\hat{q}_{0.5} \\le \\hat{q}_{0.9}$를 강제하는 것이\n아무것도 없습니다. 사후 정렬이 흔한 처방이고, 원리적으로 더 나은\n방법으로는 단조 신경망, 비교차(non-crossing) 벌점 항을 추가한 동시\n분위수 회귀 등이 있습니다. 예제에서는 공유 트렁크와 매끄러운\n데이터 덕분에 헤드 순서가 유지되지만, 이는 일반적으로 기대할 만한\n성질이 아닙니다.\n\n## Huber 손실과 강건 회귀\n\nHuber(1964)는 오늘날 그 이름이 붙은 이 구간별 손실을 제안했는데,\n가우시안 모형에서 효율적이면서도 영향력(influence)이 유계인 추정량을\n쓰기 위해서였습니다. 아주 큰 잔차 하나가 적합선을 끌 수 있는 양이\n잔차 크기 자체가 아니라 $\\delta$에 비례하도록 제한됩니다.\n\n::: {#huber-module .cell execution_count=4}\n``` {.python .cell-code}\nimport torch\nimport torch.nn as nn\n\nclass HuberLoss(nn.Module):\n    def __init__(self, delta: float = 1.0, reduction: str = \"mean\"):\n        super().__init__()\n        assert delta > 0.0\n        self.delta = float(delta)\n        self.reduction = reduction\n\n    def forward(self, pred: torch.Tensor, target: torch.Tensor) -> torch.Tensor:\n        e = target - pred\n        a = e.abs()\n        quad = 0.5 * e * e\n        lin  = self.delta * (a - 0.5 * self.delta)\n        loss = torch.where(a <= self.delta, quad, lin)\n        if self.reduction == \"mean\":  return loss.mean()\n        if self.reduction == \"sum\":   return loss.sum()\n        return loss\n```\n:::\n\n\nPyTorch에는 이미 `nn.SmoothL1Loss`(Huber를 $\\delta$로 나눈 형태)와\n`nn.HuberLoss`가 있습니다. 그럼에도 한 번쯤 직접 짜 보는 것이\n좋은 이유는 두 가지입니다. 우선 내장 손실의 API가 버전마다 다르고,\n$\\delta$가 실제로 어떤 역할을 하는지 정의를 통해 눈으로 보아야 감이\n잡히기 때문입니다. $\\delta$를 고른다는 것은 사실상 \"정상\"으로 간주할\n잡음 규모를 정하는 일입니다. $\\delta$ 이내의 잔차는 가우시안으로,\n$\\delta$를 벗어난 잔차는 하향 가중해야 할 이상치로 취급됩니다.\n$\\delta = 1.345 \\hat\\sigma$라는 어림값은 가우시안에서 점근적으로 95%\n효율을 내며, 잡음 규모를 대략 알고 있는 경우 시작점으로 쓸 만한\n값입니다.\n\n차이를 눈으로 보기 위해, 5%의 가우시안 이상치가 섞인 선형 과정에\n$y = ax + b$를 두 번 적합합니다. 한 번은 MSE, 한 번은 Huber로\n합니다.\n\n::: {#cell-fig-robust .cell execution_count=5}\n``` {.python .cell-code}\nimport torch\nimport torch.nn as nn\nimport matplotlib.pyplot as plt\n\ntorch.manual_seed(0)\nn = 400\nx = torch.linspace(-1, 1, n)\ny_clean = 2.0 * x + 0.2\ny = y_clean + 0.15 * torch.randn(n)\n\n# 이상치 주입\nmask = torch.rand(n) < 0.05\nn_out = int(mask.sum().item())\ny[mask] = y[mask] + 4.0 * torch.randn(n_out)\n\ndef fit(loss_module, iters=6000, lr=0.03):\n    a = torch.tensor(0.0, requires_grad=True)\n    b = torch.tensor(0.0, requires_grad=True)\n    opt = torch.optim.Adam([a, b], lr=lr)\n    for _ in range(iters):\n        opt.zero_grad()\n        pred = a * x + b\n        loss = loss_module(pred, y)\n        loss.backward()\n        opt.step()\n    return a.item(), b.item()\n\na_mse, b_mse = fit(nn.MSELoss())\na_hub, b_hub = fit(HuberLoss(delta=0.2))\nprint(f\"OLS   : a={a_mse:.3f}, b={b_mse:.3f}\")\nprint(f\"Huber : a={a_hub:.3f}, b={b_hub:.3f}    (true a=2.000, b=0.200)\")\n\nxs = torch.tensor([-1.05, 1.05])\nfig, ax = plt.subplots(figsize=(7, 4.2))\nax.scatter(x.numpy(), y.numpy(), s=8, alpha=0.5, label=\"data with 5% outliers\")\nax.plot(xs.numpy(), (2.0 * xs + 0.2).numpy(), \"k--\", lw=1.5, label=\"ground truth\")\nax.plot(xs.numpy(), (a_mse * xs + b_mse).numpy(), color=\"tab:red\",   lw=2,\n        label=f\"OLS  (a={a_mse:.2f}, b={b_mse:.2f})\")\nax.plot(xs.numpy(), (a_hub * xs + b_hub).numpy(), color=\"tab:green\", lw=2,\n        label=f\"Huber δ=0.2  (a={a_hub:.2f}, b={b_hub:.2f})\")\nax.set_xlabel(\"x\"); ax.set_ylabel(\"y\")\nax.set_title(\"Robustness: MSE vs Huber under 5% Gaussian outliers\")\nax.grid(alpha=0.3); ax.legend()\nplt.show()\n```\n\n::: {.cell-output .cell-output-stdout}\n```\nOLS   : a=2.186, b=0.138\nHuber : a=2.024, b=0.199    (true a=2.000, b=0.200)\n```\n:::\n\n::: {.cell-output .cell-output-display}\n![OLS(빨강)는 5% 이상치에 끌려가고, Huber(δ=0.2, 초록)는 참값(점선)에 가깝게 남습니다.](index_files/figure-html/fig-robust-output-2.png){#fig-robust width=596 height=390}\n:::\n:::\n\n\n두 적합 모두 기댓값에서는 편향이 없으므로, 데이터가 충분하면 둘\n다 참값에 수렴합니다. 그림이 보여 주는 것은 유한 표본에서의\n강건성입니다. 표본 크기가 고정되고 5% 오염이 있을 때 Huber의 기울기와\n절편이 참값에 더 가깝게 남는 이유는 각 이상치의 영향력이 $\\delta$로\n유계이기 때문입니다. 차이의 크기는 오염 비율과 이상치 규모에 따라\n달라지며, 이 문제에서는 시드에 따라 그 차이가 크지 않아도 방향은\n일관됩니다. Huber가 대가로 치르는 것은 순수 가우시안 모형에서의\n효율입니다. 이상치가 전혀 없다면 OLS보다 통계적 효율이 살짝\n떨어지며, 이 절충이 Huber(1964)의 원래 설계 지점이었습니다.\n\nHuber만이 강건 손실은 아닙니다. Cauchy나 Tukey biweight 손실은 더\n멀리 나아가서, 어떤 거리 이상에서는 기울기가 0이 되는 *재하강*\n(redescending) 성질까지 갖습니다. 대가는 손실 곡면이 비볼록이라는\n점입니다. Huber의 강점은 볼록성입니다. 평범한 옵티마이저로도 재하강\n손실에서 문제가 되는 지역 최솟값 없이 전역 최솟값에 도달합니다.\n\n## CRPS: 분포 전체를 평가하는 프로퍼 스코어\n\nMSE는 평균을, MAE는 중앙값을, 핀볼($\\tau$)은 단일 분위수를 평가합니다.\n*예측 분포 전체*가 참값을 얼마나 잘 설명하는지를 하나의 수로 재고,\n그 수가 *엄격 프로퍼(strictly proper)* — 참분포를 보고할 때에만\n기댓값 기준으로 최소화됨 — 하려면 연속형 순위 확률 점수(CRPS;\nMatheson & Winkler, 1976; Gneiting & Raftery, 2007)가 필요합니다.\n\n스칼라 관측값 $y$와 CDF가 $F$인 예측 분포에 대해\n\n$$\\operatorname{CRPS}(F, y) \\;=\\; \\int_{-\\infty}^{\\infty} \\bigl(F(z) - \\mathbf{1}\\{z \\ge y\\}\\bigr)^{2} \\, dz$$\n\n로 정의됩니다. 적분 안의 항은 모든 $z$에서 예측 CDF를 \"완벽한\"\n계단 함수 CDF(진리인 $y$에 델타)와 비교합니다. 두 가지 유용한 등가\n형태가 있습니다. $F$가 가우시안 $\\mathcal{N}(\\mu, \\sigma^2)$일 때\n적분은 닫힌 형태를 가집니다(Gneiting et al., 2005):\n\n$$\\operatorname{CRPS}\\bigl(\\mathcal{N}(\\mu, \\sigma^2), y\\bigr) =\n\\sigma \\left[\n  z\\bigl(2\\Phi(z) - 1\\bigr) + 2\\phi(z) - \\tfrac{1}{\\sqrt{\\pi}}\n\\right], \\qquad z = \\frac{y - \\mu}{\\sigma}.$$\n\n여기서 $\\Phi$와 $\\phi$는 표준정규 CDF·PDF입니다. 예측이 표본\n$x_1, \\dots, x_M$(앙상블이나 MC-Dropout 샘플)인 경우, CRPS의 유한\n표본 무편 추정량이 존재합니다(Gneiting & Raftery, 2007):\n\n$$\\widehat{\\operatorname{CRPS}}(y) =\n\\frac{1}{M} \\sum_{i=1}^{M} |x_i - y|\n- \\frac{1}{2 M^{2}} \\sum_{i=1}^{M} \\sum_{j=1}^{M} |x_i - x_j|.$$\n\n첫 항은 *정확도* — 예측 표본이 $y$에 가까울수록 보상 — 를, 둘째 항은\n*샤프니스* — 예측 표본이 지나치게 뭉쳐 있으면 벌점 — 를 잡습니다.\nCRPS는 위치 항과 산포 항의 합이며, 두 항 모두를 최소화하는 지점이\n곧 참분포입니다.\n\n::: {#crps-modules .cell execution_count=6}\n``` {.python .cell-code}\nimport torch\nimport torch.nn as nn\nimport math\n\nclass CRPSGaussianLoss(nn.Module):\n    \"\"\"\n    가우시안 예측 N(mu, sigma^2)에 대한 CRPS.\n    pred shape: (..., 2), 마지막 축 = (mu, log_sigma).\n    \"\"\"\n    def __init__(self, reduction: str = \"mean\"):\n        super().__init__()\n        self.reduction = reduction\n\n    @staticmethod\n    def _phi(z):\n        return torch.exp(-0.5 * z * z) / math.sqrt(2.0 * math.pi)\n\n    @staticmethod\n    def _Phi(z):\n        return 0.5 * (1.0 + torch.erf(z / math.sqrt(2.0)))\n\n    def forward(self, pred: torch.Tensor, target: torch.Tensor) -> torch.Tensor:\n        mu = pred[..., 0]\n        sigma = torch.nn.functional.softplus(pred[..., 1]) + 1e-6\n        z = (target - mu) / sigma\n        crps = sigma * (z * (2.0 * self._Phi(z) - 1.0)\n                        + 2.0 * self._phi(z)\n                        - 1.0 / math.sqrt(math.pi))\n        if self.reduction == \"mean\":  return crps.mean()\n        if self.reduction == \"sum\":   return crps.sum()\n        return crps\n\n\nclass CRPSEnsembleLoss(nn.Module):\n    \"\"\"\n    관측당 M개 멤버로 이루어진 앙상블 CRPS의 무편 유한표본 추정.\n    pred shape: (..., M).\n    쌍대 항의 분모를 M^2가 아니라 M(M-1)로 두어 무편성을 얻습니다.\n    \"\"\"\n    def __init__(self, reduction: str = \"mean\"):\n        super().__init__()\n        self.reduction = reduction\n\n    def forward(self, members: torch.Tensor, target: torch.Tensor) -> torch.Tensor:\n        # target을 (..., 1)로 broadcast하여 M축과 빼기 가능하게 만듦\n        M = members.shape[-1]\n        y = target.unsqueeze(-1)\n        term_a = (members - y).abs().mean(dim=-1)\n        # pairwise |x_i - x_j|를 2 M (M-1)로 나눔 -> 무편\n        diff = (members.unsqueeze(-1) - members.unsqueeze(-2)).abs()\n        term_b = diff.sum(dim=(-1, -2)) / (2.0 * M * (M - 1))\n        crps = term_a - term_b\n        if self.reduction == \"mean\":  return crps.mean()\n        if self.reduction == \"sum\":   return crps.sum()\n        return crps\n```\n:::\n\n\n가우시안 형태는 표준화된 $z = (y - \\mu) / \\sigma$만 있으면 되고,\n앙상블 형태는 표본 간 절대차만 쓰므로 $x_i$에 대해 미분 가능합니다.\n즉 앙상블을 출력하는 모델(예: 예측을 $M$번 샘플링하는 MC-Dropout\n네트워크)을 CRPS로 end-to-end 학습할 수 있습니다.\n\nCRPS가 실제로 무엇을 보상하는지 보기 위해, 고정된 $y$ 주변에서 $\\mu$\n와 $\\sigma$를 변화시켜 점수 표면을 그려 보고, \"참 $\\sigma$에서\n최솟값\" 성질을 수치적으로 확인합니다.\n\n::: {#fig-crps .cell execution_count=7}\n``` {.python .cell-code}\nimport torch, math\nimport matplotlib.pyplot as plt\n\ndef crps_gauss(y, mu, sigma):\n    z = (y - mu) / sigma\n    Phi = 0.5 * (1.0 + torch.erf(z / math.sqrt(2.0)))\n    phi = torch.exp(-0.5 * z * z) / math.sqrt(2.0 * math.pi)\n    return sigma * (z * (2.0 * Phi - 1.0) + 2.0 * phi - 1.0 / math.sqrt(math.pi))\n\nmus = torch.linspace(-3, 3, 400)\nsigs_axis = torch.linspace(0.1, 3.0, 400)\n\nfig, axes = plt.subplots(1, 2, figsize=(11, 3.6))\nfor s in (0.3, 1.0, 2.0):\n    axes[0].plot(mus, crps_gauss(torch.tensor(0.0), mus, torch.tensor(s)), lw=2, label=f\"σ={s}\")\naxes[0].set_title(\"CRPS(N(μ,σ²) | y=0) vs μ\")\naxes[0].set_xlabel(\"forecast mean μ\"); axes[0].set_ylabel(\"CRPS\")\naxes[0].legend(); axes[0].grid(alpha=0.3)\n\nfor mu in (0.0, 0.5, 1.0):\n    axes[1].plot(sigs_axis, crps_gauss(torch.tensor(0.0), torch.tensor(mu), sigs_axis), lw=2, label=f\"|μ|={mu}\")\naxes[1].set_title(\"CRPS(N(μ,σ²) | y=0) vs σ\")\naxes[1].set_xlabel(\"forecast std σ\"); axes[1].set_ylabel(\"CRPS\")\naxes[1].legend(); axes[1].grid(alpha=0.3)\nfig.tight_layout()\nplt.show()\n\ntorch.manual_seed(0)\ny_samples = torch.randn(4000)   # 참분포 N(0,1)\nsigs = torch.linspace(0.05, 4.0, 200)\navg_crps = torch.stack([crps_gauss(y_samples, torch.tensor(0.0), s).mean() for s in sigs])\nprint(f\"argmin σ (should be near 1.0): {sigs[avg_crps.argmin()].item():.3f}\")\n\nfig, ax = plt.subplots(figsize=(6.4, 3.6))\nax.plot(sigs, avg_crps, lw=2)\nax.axvline(1.0, color=\"k\", ls=\"--\", lw=1, label=\"true σ=1\")\nax.set_xlabel(\"forecast σ (with correct mean μ=0)\")\nax.set_ylabel(\"average CRPS\")\nax.set_title(\"CRPS is minimised at the true σ when forecast mean is correct\")\nax.grid(alpha=0.3); ax.legend()\nplt.show()\n```\n\n::: {.cell-output .cell-output-display}\n![y=0에 대한 가우시안 CRPS. 왼쪽: 세 σ에서 μ의 함수. 오른쪽: 세 |μ|에서 σ의 함수. 아래: 평균이 정확할 때 N(0,1)에서 뽑은 4000개 샘플의 평균 CRPS는 σ=1에서 뚜렷한 최소를 가집니다.](index_files/figure-html/fig-crps-output-1.png){#fig-crps-1 width=1046 height=336}\n:::\n\n::: {.cell-output .cell-output-stdout}\n```\nargmin σ (should be near 1.0): 0.983\n```\n:::\n\n::: {.cell-output .cell-output-display}\n![](index_files/figure-html/fig-crps-output-3.png){#fig-crps-2 width=557 height=346}\n:::\n:::\n\n\n첫 두 패널을 같이 보는 것이 좋습니다. $\\sigma$를 키우면 $y$ 지점의\n벌점은 낮아지지만 그 외 모든 지점의 벌점이 오릅니다. 넓은 예측은\n$\\mu$에 대한 오차를 헤지하는 셈입니다. 이것이 프로퍼 스코어의 실질적\n의미입니다. 참 $\\mu$에서만 참 $\\sigma$가 최적이 되므로, 예측이\n불확실성을 부풀려 점수를 속일 방법이 없습니다. 마지막 패널은 이를\n수치적으로 확인해 줍니다. $\\mathcal{N}(0, 1)$에서 뽑은 4000개\n표본에 대해 $\\sigma$에 걸친 평균 CRPS의 argmin은 $\\sigma \\approx 1$\n에 놓입니다.\n\n결정론적 예측(점 질량)에서 CRPS는 MAE로 환원됩니다. $\\hat{y}$에\n델타인 예측은 $\\operatorname{CRPS} = |y - \\hat{y}|$입니다. 유용한\n정합성 검사이자 동시에, 점 예측을 CRPS로 평가하는 것은 사실상\nMAE로 평가하는 것과 같다는 뜻이기도 합니다. CRPS를 쓰기 전에 확률\n모델을 먼저 선택해야 합니다.\n\n## 어떤 손실이 언제 옳은가\n\n핀볼은 후속 비용이 비대칭 — 저평가와 고평가의 벌점이 다를 때 —\n적합한 손실입니다. 소매 재고, 전력 급전, 리스크 분위수가 자연스러운\n대상입니다. 공유 트렁크에 여러 분위수 헤드를 붙이면 분포 전체의\n빠르고 종종 놀랍도록 준수한 근사가 되지만, 분포 형태 자체는 남지\n않고 학습한 분위수 수준만 남습니다. 헤드 비교차는 자동으로 보장되지\n않으며, 핀볼은 0에서 미분 불가능합니다. 둘 다 관리 가능한 문제이고,\n어느 것도 핀볼을 피해야 할 이유는 아닙니다.\n\nHuber는 오차의 꼬리가 두꺼우면서도 예측 목표가 여전히 평균에\n가까운 양일 때 적합합니다. $\\delta$는 가우시안에서의 통계적\n효율과 이상치에 대한 강건성 사이의 절충 하이퍼파라미터이므로,\n1.0으로 놓고 넘어가지 말고 검증 성능이나 잡음 규모 추정으로\n조정하는 것이 좋습니다. Huber가 근본적인 모델 오설정을 구해 주지는\n않습니다. 참 조건부 분포가 비대칭이면 Huber의 평균형 목표는 여전히\n기댓값 기준으로 틀리며, 다만 꼬리에 덜 민감할 뿐입니다.\n\nCRPS는 산출물이 점이 아니라 분포일 때 옳은 손실입니다. CRPS를 직접\n최소화하면 네트워크가 분포 파라미터($\\mu, \\sigma$)를 내거나 앙상블\n표본을 내도록 학습됩니다. 가우시안 형태가 가장 쉬운 시작점이고,\n앙상블 형태는 분포 형태를 고정하지 않지만 관측당 $M$개 표본을\n만들어 내는 장치(베이지안 근사, MC-Dropout, 입력에 잠재 잡음\nconcat)가 필요합니다. 둘 다 프로퍼 스코어이며, 해석 가능한 특수\n경우로 환원되고, 캘리브레이션과 샤프니스가 하나의 목적 함수 안에서\n동시에 최적화됩니다.\n\nMSE가 기본으로서 방어 가능한 것은 세 조건이 함께 성립할 때뿐입니다.\n사용자가 실제로 원하는 것이 평균이고, 잡음이 대체로 대칭이며 꼬리가\n지나치게 두껍지 않고, 후속 결정에서 불확실성이 필요 없을 때입니다.\n이 중 하나라도 무너지는 순간, 위의 세 손실 중 하나가 운영 환경에서\n모델이 실제로 평가받는 기준에 더 가깝습니다.\n\n## 한계와 다루지 않은 것\n\n세 손실 각각에는 명시해 둘 만한 실무적 제약이 있습니다. 핀볼의\n등가 집합 비유일성은 일반적인 연속형 데이터에서는 드러나지 않지만,\n정수형이나 크게 양자화된 목표에서는 최적화가 정체될 수 있습니다.\nHuber의 $\\delta$는 잡음 규모가 시간에 따라 변하면 적절한 범위를\n벗어날 수 있고, 이동 중앙값 절대편차(MAD)로 $\\delta$를 갱신하는\n적응식 접근이 있지만 재현성과 모니터링은 복잡해집니다. CRPS의\n가우시안 형태는 두꺼운 꼬리(금융 수익률, 극한 기상)가 위배하는\n가우시안 형태를 가정하며, 앙상블이나 Student-$t$ 헤드로 옮기는 것은\n비용을 요구합니다. 앙상블 출력을 학습하면 메모리가 늘어나고, 쌍대\n합을 효율적으로 구현하지 않으면 관측당 계산량이 $O(M^{2})$가 됩니다.\n\n여기서는 다변량 CRPS(Energy Score, Variogram Score), 시간\n구조를 반영한 손실(수평선별 평균 CRPS vs. 수평선 결합 다변량\nCRPS), 그리고 여러 목표를 결합한 손실(예: 중앙값은 핀볼, 극단은\nInterval Score) 등은 다루지 않았습니다. 모델링 목표가 정해지면\n자연스레 이어질 다음 단계입니다.\n\n## 참고문헌\n\nGneiting, T., Raftery, A. E., Westveld, A. H., & Goldman, T. (2005).\nCalibrated probabilistic forecasting using ensemble model output\nstatistics and minimum CRPS estimation. *Monthly Weather Review*,\n133(5), 1098–1118.\n[https://doi.org/10.1175/MWR2904.1](https://doi.org/10.1175/MWR2904.1)\n\nGneiting, T., & Raftery, A. E. (2007). Strictly proper scoring\nrules, prediction, and estimation. *Journal of the American\nStatistical Association*, 102(477), 359–378.\n[https://doi.org/10.1198/016214506000001437](https://doi.org/10.1198/016214506000001437)\n\nHuber, P. J. (1964). Robust estimation of a location parameter.\n*The Annals of Mathematical Statistics*, 35(1), 73–101.\n[https://doi.org/10.1214/aoms/1177703732](https://doi.org/10.1214/aoms/1177703732)\n\nKoenker, R., & Bassett, G. (1978). Regression quantiles.\n*Econometrica*, 46(1), 33–50.\n[https://doi.org/10.2307/1913643](https://doi.org/10.2307/1913643)\n\nMatheson, J. E., & Winkler, R. L. (1976). Scoring rules for\ncontinuous probability distributions. *Management Science*, 22(10),\n1087–1096.\n[https://doi.org/10.1287/mnsc.22.10.1087](https://doi.org/10.1287/mnsc.22.10.1087)\n\n",
    "supporting": [
      "index_files"
    ],
    "filters": [],
    "includes": {}
  }
}